flask_skinny/__init__.py
flask_skinny/skinny.py
flask_skinny-0.1.2.dist-info/LICENSE
flask_skinny-0.1.2.dist-info/METADATA
flask_skinny-0.1.2.dist-info/WHEEL
flask_skinny-0.1.2.dist-info/top_level.txt
flask_skinny-0.1.2.dist-info/RECORD
